pymzxml-0.1.1.dist-info/RECORD
pymzxml-0.1.1.dist-info/WHEEL
pymzxml-0.1.1.dist-info/METADATA
pymzxml-0.1.1.dist-info/LICENSE
pymzxml-0.1.1.dist-info/top_level.txt
pymzxml/__init__.py
pymzxml/ramp/src/ramp_base64.cpp
pymzxml/ramp/src/ramp_base64.h
pymzxml/ramp/src/fd_ramp.cpp
pymzxml/ramp/src/random_access_gzFile.h
pymzxml/ramp/src/random_access_gzFile.cpp
pymzxml/ramp/src/ramp.cpp
pymzxml/ramp/src/fd_ramp.h
pymzxml/ramp/src/ramp.h
pymzxml/mzxmlwriter/__init__.py
pymzxml/mzxmlwriter/writer.py
pymzxml/rampy/__init__.py
pymzxml/rampy/rampy.py
pymzxml/rampy/ramp.cpython-310-x86_64-linux-gnu.so
