Metadata-Version: 2.1
Name: pymzxml
Version: 0.1.1
Summary: A set of functions to read and write mzXML files
Author-email: Pedrioli Patrick <pedrioli@gmail.com>
License: GPLv3
License-File: LICENSE
Requires-Dist: numpy
Provides-Extra: dev
Requires-Dist: pre-commit ; extra == 'dev'
Requires-Dist: black ; extra == 'dev'
Requires-Dist: isort ; extra == 'dev'
Requires-Dist: flake8 ; extra == 'dev'
Requires-Dist: autoflake ; extra == 'dev'
Requires-Dist: docformatter ; extra == 'dev'
